[
  {
    "title": "Getting to Know Leads Map",
    "description": "An introduction to Leads Map and how it helps you find and manage leads smarter.",
    "videoUrl": "https://youtu.be/IDyWF8-r8bI?si=uBeEueNYWj8h0tae"
  },
  {
    "title": "Leads Map + Merchant Genius (Part 1)",
    "description": "Learn how to extract and use email leads from e-commerce merchants with Merchant Genius.",
    "videoUrl": "https://youtu.be/NHtGdUOihVA?si=MldMfoP9OJB1hRbg"
  },
  {
    "title": "Leads Map + Merchant Genius (Part 2)",
    "description": "See how to visit websites one by one and reach out using available contact details.",
    "videoUrl": "https://youtu.be/Rb623eZRnG8?si=gTD3UxwQW6M8gV0_"
  },
  {
    "title": "Leads Map + Bootleads",
    "description": "Find and connect with prospects using social media URLs for direct outreach.",
    "videoUrl": "https://youtu.be/nFzRW3vF0QA?si=qJABC9n-0kOmnIOn"
  },
  {
    "title": "Leads Map + EachSpy",
    "description": "Get more detailed information about your leads to qualify and target them better.",
    "videoUrl": "https://youtu.be/3BzgqUdj_Pc?si=ChtCF2jZ5K6lb2OD"
  },
  {
    "title": "Using Leads Map Local Storage",
    "description": "Learn how to extract and manage leads saved in your local storage file.",
    "videoUrl": "https://youtu.be/Qu5GZRus0ew?si=dnBits3arK9Wg1Ux"
  }
]
